lua_imports/__init__.py
lua_imports/importer.py
lua_imports-1.0.0.dist-info/LICENSE
lua_imports-1.0.0.dist-info/METADATA
lua_imports-1.0.0.dist-info/WHEEL
lua_imports-1.0.0.dist-info/top_level.txt
lua_imports-1.0.0.dist-info/RECORD
